synphot-1.6.0.dist-info/RECORD
synphot-1.6.0.dist-info/WHEEL
synphot-1.6.0.dist-info/top_level.txt
synphot-1.6.0.dist-info/METADATA
synphot-1.6.0.dist-info/licenses/LICENSE.rst
synphot/binning.py
synphot/observation.py
synphot/thermal.py
synphot/config.py
synphot/synphot_utils.cpython-310-darwin.so
synphot/units.py
synphot/version.py
synphot/compat.py
synphot/models.py
synphot/compat_specutils.py
synphot/reddening.py
synphot/__init__.py
synphot/spectrum.py
synphot/utils.py
synphot/specio.py
synphot/exceptions.py
synphot/blackbody.py
synphot/tests/test_utils.py
synphot/tests/test_binning.py
synphot/tests/test_specio.py
synphot/tests/test_thermal.py
synphot/tests/test_observation.py
synphot/tests/test_spectrum_misc.py
synphot/tests/__init__.py
synphot/tests/test_blackbody.py
synphot/tests/test_spectrum_bandpass.py
synphot/tests/test_units.py
synphot/tests/test_models.py
synphot/tests/test_reddening.py
synphot/tests/test_integrator.py
synphot/tests/test_spectrum_source.py
synphot/tests/data/cos_fuv_g130m_c1309_psa.fits
synphot/tests/data/us7.txt
synphot/tests/data/wfc3_ir_g141_src_003_th.fits
synphot/tests/data/stis_fuv_f25ndq2_mjd58300_0822774.fits
synphot/tests/data/grw_70d5824_stisnic_005.fits
synphot/tests/data/k93_4500_0_5_rn_box.fits
synphot/tests/data/hst_acs_hrc_f555w_x_grw70d5824.fits
synphot/tests/data/stis_fuv_f25ndq2_binset.bin
synphot/tests/data/milkyway_diffuse_001.fits
synphot/tests/data/hst_acs_hrc_f555w.fits
synphot/tests/data/qso_template_001.dat
synphot/tests/data/hst_acs_hrc_f850lp.fits
synphot/filter_parameterization/__init__.py
synphot/filter_parameterization/filter_fft.py
synphot/filter_parameterization/tests/test_filter_fft.py
synphot/filter_parameterization/tests/__init__.py
synphot/filter_parameterization/tests/data/fft_test_data.fits
